bourbaki/__init__.py
bourbaki/regex/__init__.py
bourbaki/regex/base.py
bourbaki/regex/utils.py
bourbaki.regex-0.2.2.dist-info/LICENSE
bourbaki.regex-0.2.2.dist-info/METADATA
bourbaki.regex-0.2.2.dist-info/WHEEL
bourbaki.regex-0.2.2.dist-info/top_level.txt
bourbaki.regex-0.2.2.dist-info/zip-safe
bourbaki.regex-0.2.2.dist-info/RECORD
